[null,{"name":"elo","temp":"xdd","event-type":"6","actions":[{"member":"2","varName":"xdd","info":"16","storage":"1","varName2":"powod","name":"Store Member Info"},{"info":"1","find":"✈przyloty✈","storage":"1","varName":"xdd","name":"Find Channel"},{"title":"**Witamy**","author":"","color":"#ffff00","url":"","authorIcon":"","authorUrl":"","imageUrl":"","thumbUrl":"${tempVars(\"powod\")}","timestamp":"true","text":"","year":"","month":"","day":"","hour":"","minute":"","second":"","storage":"1","varName":"jdd","name":"Create Embed Message"},{"storage":"1","varName":"jdd","message":"${tempVars(\"xdd\")} Witaj na serwerze **XzoneRP**\n","name":"Set Embed Description"},{"storage":"1","varName":"jdd","channel":"5","varName2":"xdd","storage3":"0","varName3":"","name":"Send Embed Message"}],"_id":"HGQqU"},{"name":"jdd","permissions":"ADMINISTRATOR","restriction":"1","actions":[{"token":"","user":"","pass":"","url":"https://servers-live.fivem.net/api/servers/single/134.255.233.193:32324","path":"Data.clients","storage":"1","varName":"powod","debugMode":"1","headers":"","name":"Store Json From WebAPI"},{"token":"","user":"","pass":"","url":"https://servers-live.fivem.net/api/servers/single/134.255.233.193:32324","path":"Data.sv_maxclients","storage":"1","varName":"xdd","debugMode":"1","headers":"","name":"Store Json From WebAPI"},{"gameName":"${tempVars(\"powod\")} / ${tempVars(\"xdd\")} Graczy","gameLink":"","name":"Set Bot Game"}],"event-type":"2","temp":"5","_id":"OZlaV"}]